dramatiq_dashboard/__init__.py
dramatiq_dashboard/application.py
dramatiq_dashboard/csrf.py
dramatiq_dashboard/filters.py
dramatiq_dashboard/http.py
dramatiq_dashboard/interface.py
dramatiq_dashboard/middleware.py
dramatiq_dashboard/redis/dispatch.lua
dramatiq_dashboard/templates/_action.html
dramatiq_dashboard/templates/_base.html
dramatiq_dashboard/templates/_grid.html
dramatiq_dashboard/templates/_panel.html
dramatiq_dashboard/templates/_tabs.html
dramatiq_dashboard/templates/_timestamp.html
dramatiq_dashboard/templates/dashboard.html
dramatiq_dashboard/templates/job.html
dramatiq_dashboard/templates/queue.html
dramatiq_dashboard-0.4.0.dist-info/COPYING
dramatiq_dashboard-0.4.0.dist-info/COPYING.LESSER
dramatiq_dashboard-0.4.0.dist-info/METADATA
dramatiq_dashboard-0.4.0.dist-info/WHEEL
dramatiq_dashboard-0.4.0.dist-info/top_level.txt
dramatiq_dashboard-0.4.0.dist-info/RECORD
