Metadata-Version: 2.1
Name: dramatiq-dashboard
Version: 0.4.0
Summary: A dashboard for Dramatiq (Redis-only!).
Author: Bogdan Popa
Author-email: bogdan@cleartype.io
License: UNKNOWN
Platform: UNKNOWN
Classifier: Programming Language :: Python :: 3.6
Classifier: Programming Language :: Python :: 3.7
Classifier: Programming Language :: Python :: 3 :: Only
Classifier: Topic :: System :: Distributed Computing
Classifier: License :: OSI Approved :: GNU Lesser General Public License v3 or later (LGPLv3+)
Requires-Python: >=3.6
License-File: COPYING
License-File: COPYING.LESSER
Requires-Dist: dramatiq[redis] (<2.0,>=1.6)
Requires-Dist: jinja2 (>=2)
Requires-Dist: redis (<5.0,>=2.0)
Requires-Dist: dataclasses ; python_version < "3.7"
Provides-Extra: all
Provides-Extra: dev
Requires-Dist: alabaster ; extra == 'dev'
Requires-Dist: sphinx (<1.8) ; extra == 'dev'
Requires-Dist: sphinxcontrib-napoleon ; extra == 'dev'
Requires-Dist: flake8 ; extra == 'dev'
Requires-Dist: flake8-bugbear ; extra == 'dev'
Requires-Dist: flake8-quotes ; extra == 'dev'
Requires-Dist: isort ; extra == 'dev'
Requires-Dist: bumpversion ; extra == 'dev'
Requires-Dist: hiredis ; extra == 'dev'
Requires-Dist: twine ; extra == 'dev'
Requires-Dist: wheel ; extra == 'dev'
Requires-Dist: pytest ; extra == 'dev'
Requires-Dist: pytest-benchmark[histogram] ; extra == 'dev'
Requires-Dist: pytest-cov ; extra == 'dev'
Requires-Dist: tox ; extra == 'dev'
